extractini/__init__.py
extractini/console.py
extractini-1.0.1.dist-info/entry_points.txt
extractini-1.0.1.dist-info/LICENSE
extractini-1.0.1.dist-info/WHEEL
extractini-1.0.1.dist-info/METADATA
extractini-1.0.1.dist-info/RECORD
