Metadata-Version: 2.1
Name: extractini
Version: 1.0.1
Summary: extractini is a command-line application to extract a single option from an INI file
Home-page: https://github.com/AzMoo/extractini/
License: MIT
Author: Matt Magin
Author-email: matt.magin@cmv.com.au
Requires-Python: >=3.5,<4.0
Classifier: License :: OSI Approved :: MIT License
Classifier: Programming Language :: Python :: 3
Classifier: Programming Language :: Python :: 3.5
Classifier: Programming Language :: Python :: 3.6
Classifier: Programming Language :: Python :: 3.7
Requires-Dist: click (>=6.7,<7.0)
